olca_schema/__init__.py
olca_schema/schema.py
olca_schema/zipio.py
olca_schema/units/__init__.py
olca_schema/units/units.csv
olca_schema-2.2.2.dist-info/METADATA
olca_schema-2.2.2.dist-info/WHEEL
olca_schema-2.2.2.dist-info/top_level.txt
olca_schema-2.2.2.dist-info/RECORD
