Metadata-Version: 2.1
Name: olca_schema
Version: 2.2.2
Summary: A package for reading and writing data sets in the openLCA schema format.
Project-URL: Homepage, https://github.com/GreenDelta/olca-schema
Project-URL: Bug Tracker, https://github.com/GreenDelta/olca-schema/issues
Keywords: openLCA,life cycle assessment,LCA
Classifier: Development Status :: 2 - Pre-Alpha
Classifier: Programming Language :: Python :: 3
Classifier: License :: CC0 1.0 Universal (CC0 1.0) Public Domain Dedication
Classifier: Operating System :: OS Independent
Classifier: Environment :: Console
Classifier: Intended Audience :: Science/Research
Classifier: Topic :: Utilities
Requires-Python: >=3.9
